tinvest/__init__.py
tinvest/__main__.py
tinvest/apis.py
tinvest/apis.pyi
tinvest/cli/__init__.py
tinvest/cli/app.py
tinvest/cli/openapi.py
tinvest/clients.py
tinvest/config.py
tinvest/constants.py
tinvest/exceptions.py
tinvest/schemas.py
tinvest/streaming.py
tinvest/typedefs.py
tinvest/utils.py
tinvest-3.0.4.dist-info/entry_points.txt
tinvest-3.0.4.dist-info/LICENSE
tinvest-3.0.4.dist-info/WHEEL
tinvest-3.0.4.dist-info/METADATA
tinvest-3.0.4.dist-info/RECORD
