Metadata-Version: 2.1
Name: tinvest
Version: 3.0.4
Summary: Tinkoff Invest
Home-page: https://pypi.org/project/tinvest
License: MIT
Author: Danil Akhtarov
Author-email: daxartio@gmail.com
Requires-Python: >=3.8,<4.0
Classifier: License :: OSI Approved :: MIT License
Classifier: Programming Language :: Python :: 3
Classifier: Programming Language :: Python :: 3.8
Classifier: Programming Language :: Python :: 3.9
Provides-Extra: cli
Provides-Extra: orjson
Provides-Extra: uvloop
Requires-Dist: aiohttp (>=3.6,<4.0)
Requires-Dist: orjson (>=3.4,<4.0); extra == "orjson"
Requires-Dist: pydantic (>=1.2,<2.0)
Requires-Dist: requests (>=2.22,<3.0)
Requires-Dist: typer (>=0.3.2,<0.4.0); extra == "cli"
Requires-Dist: uvloop (>=0.15,<0.16); extra == "uvloop"
Project-URL: Repository, https://github.com/daxartio/tinvest
